eumdac/__init__.py
eumdac/__version__.py
eumdac/cli.py
eumdac/collection.py
eumdac/config.py
eumdac/customisation.py
eumdac/datastore.py
eumdac/datatailor.py
eumdac/download_app.py
eumdac/endpoints.ini
eumdac/errors.py
eumdac/fake.py
eumdac/job_id.py
eumdac/logging.py
eumdac/order.py
eumdac/product.py
eumdac/subscription.py
eumdac/tailor_app.py
eumdac/tailor_models.py
eumdac/token.py
eumdac_tmp-2.0.0rc3.dist-info/AUTHORS.txt
eumdac_tmp-2.0.0rc3.dist-info/LICENSE.txt
eumdac_tmp-2.0.0rc3.dist-info/LICENSE_APACHE_v2.txt
eumdac_tmp-2.0.0rc3.dist-info/LICENSE_MIT.txt
eumdac_tmp-2.0.0rc3.dist-info/METADATA
eumdac_tmp-2.0.0rc3.dist-info/WHEEL
eumdac_tmp-2.0.0rc3.dist-info/entry_points.txt
eumdac_tmp-2.0.0rc3.dist-info/top_level.txt
eumdac_tmp-2.0.0rc3.dist-info/RECORD
