Metadata-Version: 2.1
Name: eumdac-tmp
Version: 2.0.0rc3
Summary: EUMETSAT Data Access Client
Home-page: https://gitlab.eumetsat.int/eumetlab/data-services/eumdac
Author: EUMETSAT
Author-email: ops@eumetsat.int
License: MIT
Classifier: Development Status :: 5 - Production/Stable
Classifier: Intended Audience :: Developers
Classifier: Programming Language :: Python
Classifier: Programming Language :: Python :: 3
Classifier: Programming Language :: Python :: 3.7
Classifier: Programming Language :: Python :: 3.8
Classifier: Programming Language :: Python :: 3.9
Classifier: Programming Language :: Python :: Implementation :: CPython
Classifier: Programming Language :: Python :: Implementation :: PyPy
Classifier: Operating System :: OS Independent
Requires-Python: >=3.7
License-File: LICENSE.txt
License-File: LICENSE_APACHE_v2.txt
License-File: LICENSE_MIT.txt
License-File: AUTHORS.txt
Requires-Dist: requests (>=2.5.0)
Requires-Dist: pyyaml (>=5.1)
Provides-Extra: test
Requires-Dist: mypy ; extra == 'test'
Requires-Dist: pytest ; extra == 'test'
Requires-Dist: pytest-cov ; extra == 'test'
Requires-Dist: responses ; extra == 'test'
Requires-Dist: types-requests ; extra == 'test'
Requires-Dist: types-setuptools ; extra == 'test'
